plotly_light/__init__.py
plotly_light/_bar.py
plotly_light/_box.py
plotly_light/_config.py
plotly_light/_const.py
plotly_light/_crawl.py
plotly_light/_histogram.py
plotly_light/_image.py
plotly_light/_layout.py
plotly_light/_line.py
plotly_light/_rectangle.py
plotly_light/_renderer.py
plotly_light/_scatter.py
plotly_light/_show.py
plotly_light/_type.py
plotly_light/_venn.py
plotly_light/default.py
plotly_light-2.0.1.dist-info/licenses/LICENSE
plotly_light-2.0.1.dist-info/METADATA
plotly_light-2.0.1.dist-info/WHEEL
plotly_light-2.0.1.dist-info/top_level.txt
plotly_light-2.0.1.dist-info/RECORD
