Metadata-Version: 2.4
Name: plotly-light
Version: 2.0.1
Summary: A wrapper of Plotly Python for lightweight plots
Author-email: Yoshihiko Suzuki <yoshi.suzuki.1992@gmail.com>
License: MIT License
Project-URL: Homepage, https://github.com/yoshihikosuzuki/plotly_light
Requires-Python: >=3.7
License-File: LICENSE
Requires-Dist: plotly>=6.0
Requires-Dist: kaleido
Requires-Dist: notebook>=7.0
Requires-Dist: anywidget>=0.9.13
Requires-Dist: numpy
Requires-Dist: matplotlib
Requires-Dist: matplotlib-venn
Requires-Dist: ipython
Requires-Dist: pandas
Requires-Dist: scikit-image
Requires-Dist: logzero
Requires-Dist: ipynb-path
Dynamic: license-file
